{
  "author": "BuildFire",
  "pluginName": "Punch Card",
  "pluginDescription": "Say farewell to conventional loyalty cards and embrace a seamless, digital punch card experience. With this feature, your users effortlessly earn rewards with every purchase – just 'punch' their virtual card, and witness their loyalty points grow. Our user-friendly design ensures tracking their loyalty journey and redeeming rewards is a breeze.",
  "supportEmail": "support@buildfire.com",
  "requireLogin": true,
  "control": {
    "content": {
      "enabled": true
    },
    "design": {
      "enabled": false
    },
    "settings": {
      "enabled": true
    },
    "language": {
      "enabled": false,
      "languageJsonPath": "resources/languages.json"
    },
    "customTabs": [
      {
        "title": "Design",
        "url": "/design/index.html"
      },
      {
        "title": "Tests",
        "url": "/tests/index.html?random=false&stopOnSpecFailure=true"
      }
    ],
    "cssInjection": {
      "enabled": false,
      "layouts": [
        {
          "name": "Layout 1",
          "imageUrl": "resources/layouts/layout1.png",
          "cssPath": "widget/layouts/layout1.css"
        }
      ]
    }
  },
  "keywords": "Loyalty program, digital rewards, punch card, customer retention, loyalty points, rewards system, mobile stamping, virtual punch card, purchase tracking, incentive program, mobile loyalty, points accumulation, customer engagement, redeemable points, retail rewards",
  "features": [],
  "languages": ["en"]
}
